jwpackage/__init__.py
jwpackage/authentication/JWT_auth.py
jwpackage/authentication/__init__.py
jwpackage/authentication/auth.py
jwpackage/authentication/exceptions.py
jwpackage-0.1.3.dist-info/METADATA
jwpackage-0.1.3.dist-info/WHEEL
jwpackage-0.1.3.dist-info/top_level.txt
jwpackage-0.1.3.dist-info/RECORD
