Metadata-Version: 2.1
Name: jwpackage
Version: 0.1.3
Summary: Justwicks package
Author: Preetham Puttaswamy
Author-email: <youremail@email.com>
License: UNKNOWN
Keywords: python,jwpackage
Platform: UNKNOWN
Classifier: Development Status :: 3 - Alpha
Classifier: Intended Audience :: Education
Classifier: Programming Language :: Python :: 3
Classifier: Operating System :: MacOS :: MacOS X
Classifier: Operating System :: Microsoft :: Windows
Requires-Dist: PyJWT (==2.6.0)
Requires-Dist: fastapi (==0.75.0)
Requires-Dist: cryptography (==39.0.2)
Requires-Dist: pyOpenSSL (==23.0.0)
Requires-Dist: python-dotenv (==0.19.2)
